memorag/__init__.py
memorag/agent.py
memorag/memorag.py
memorag/memorag_lite.py
memorag/prompt.py
memorag/retrieval.py
memorag-0.1.5.dist-info/LICENSE
memorag-0.1.5.dist-info/METADATA
memorag-0.1.5.dist-info/WHEEL
memorag-0.1.5.dist-info/top_level.txt
memorag-0.1.5.dist-info/RECORD
