Metadata-Version: 2.1
Name: memorag
Version: 0.1.5
Summary: A Python package for memory-augmented retrieval-augmented generation
Author: Tommy Chien
Author-email: tommy@chien.io
Classifier: Programming Language :: Python :: 3.10
Classifier: Programming Language :: Python :: 3.11
Classifier: License :: OSI Approved :: MIT License
Classifier: Operating System :: OS Independent
Requires-Python: >=3.10
License-File: LICENSE
Requires-Dist: transformers>=4.43.1
Requires-Dist: deepspeed>=0.14.0
Requires-Dist: minference==0.1.5
Requires-Dist: triton==2.3.1
Requires-Dist: accelerate
Requires-Dist: datasets
Requires-Dist: rouge
Requires-Dist: fuzzywuzzy
Requires-Dist: jieba
Requires-Dist: python-Levenshtein
Requires-Dist: seaborn
Requires-Dist: langdetect
Requires-Dist: tiktoken
Requires-Dist: openai
Requires-Dist: semantic-text-splitter
